cwlgen/__init__.py
cwlgen/commandlinebinding.py
cwlgen/commandlinetool.py
cwlgen/common.py
cwlgen/import_cwl.py
cwlgen/requirements.py
cwlgen/utils.py
cwlgen/version.py
cwlgen/workflow.py
cwlgen/workflowdeps.py
cwlgen_kclhi-0.4.0.dist-info/LICENSE.txt
cwlgen_kclhi-0.4.0.dist-info/METADATA
cwlgen_kclhi-0.4.0.dist-info/WHEEL
cwlgen_kclhi-0.4.0.dist-info/top_level.txt
cwlgen_kclhi-0.4.0.dist-info/RECORD
