Metadata-Version: 2.1
Name: cwlgen-kclhi
Version: 0.4.0
Summary: Generation of CWL programmatically. Available types: Workflow, CommandLineTool and Requirements
Home-page: UNKNOWN
Author: Kenzo-Hugo Hillion and Herve Menager
Author-email: kehillio@pasteur.fr
License: MIT
Keywords: cwl
Platform: UNKNOWN
Classifier: Development Status :: 4 - Beta
Classifier: Topic :: Scientific/Engineering :: Bio-Informatics
Classifier: Intended Audience :: Developers
Classifier: Intended Audience :: Science/Research
Classifier: Environment :: Console
Requires-Dist: ruamel.yaml (<0.16.6,>=0.12.4)
